lib_memvid-1.0.4.dist-info/licenses/LICENSE
memvid/__init__.py
memvid/chat.py
memvid/config.py
memvid/docker_manager.py
memvid/encoder.py
memvid/index.py
memvid/interactive.py
memvid/llm_client.py
memvid/retriever.py
memvid/utils.py
lib_memvid-1.0.4.dist-info/METADATA
lib_memvid-1.0.4.dist-info/WHEEL
lib_memvid-1.0.4.dist-info/top_level.txt
lib_memvid-1.0.4.dist-info/RECORD
