Metadata-Version: 2.4
Name: lib-memvid
Version: 1.0.4
Summary: Video-based AI memory library for fast semantic search and retrieval
Classifier: Development Status :: 3 - Alpha
Classifier: Intended Audience :: Developers
Classifier: Topic :: Software Development :: Libraries :: Python Modules
Classifier: Topic :: Scientific/Engineering :: Artificial Intelligence
Classifier: Topic :: Multimedia :: Video
Classifier: License :: OSI Approved :: MIT License
Classifier: Programming Language :: Python :: 3
Classifier: Programming Language :: Python :: 3.8
Classifier: Programming Language :: Python :: 3.9
Classifier: Programming Language :: Python :: 3.10
Classifier: Programming Language :: Python :: 3.11
Requires-Python: >=3.8
License-File: LICENSE
Requires-Dist: qrcode[pil]>=7.3
Requires-Dist: opencv-python>=4.5.0
Requires-Dist: opencv-contrib-python>=4.5.0
Requires-Dist: sentence-transformers>=2.2.0
Requires-Dist: numpy<2.0.0,>=1.21.0
Requires-Dist: tqdm>=4.50.0
Requires-Dist: faiss-cpu>=1.7.0
Requires-Dist: Pillow>=9.0.0
Requires-Dist: python-dotenv>=0.19.0
Requires-Dist: PyPDF2>=3.0.0
Provides-Extra: dev
Requires-Dist: pytest>=7.0.0; extra == "dev"
Requires-Dist: pytest-cov>=4.0.0; extra == "dev"
Requires-Dist: black>=23.0.0; extra == "dev"
Requires-Dist: flake8>=6.0.0; extra == "dev"
Provides-Extra: llm
Requires-Dist: openai>=1.0.0; extra == "llm"
Requires-Dist: google-genai>=1.39.1; extra == "llm"
Requires-Dist: anthropic>=0.52.0; extra == "llm"
Provides-Extra: epub
Requires-Dist: beautifulsoup4>=4.0.0; extra == "epub"
Requires-Dist: ebooklib>=0.18; extra == "epub"
Provides-Extra: web
Requires-Dist: fastapi>=0.100.0; extra == "web"
Requires-Dist: gradio>=4.0.0; extra == "web"
Dynamic: classifier
Dynamic: description
Dynamic: description-content-type
Dynamic: license-file
Dynamic: provides-extra
Dynamic: requires-dist
Dynamic: requires-python
Dynamic: summary
